<!DOCTYPE x1.xml>
<course>
    <courseInfo security="8/Pz8=" new="false" alias="新手符号过关考试" courseType="nov-symbol-exam"/>
    <content>
        <item display="" display1="" id="0" comparision="@%\/}"/>
        <item display="" display1="" id="1" comparision="?`!?["/>
        <item display="" display1="" id="2" comparision="&lt;?*[&lt;"/>
        <item display="" display1="" id="3" comparision="_':/!"/>
        <item display="" display1="" id="4" comparision="~~~_,"/>
        <item display="" display1="" id="5" comparision=">#*}}"/>
        <item display="" display1="" id="6" comparision="-~&amp;&quot;&lt;"/>
        <item display="" display1="" id="7" comparision="{$\::"/>
        <item display="" display1="" id="8" comparision="$!?@;"/>
        <item display="" display1="" id="9" comparision="#$$?'"/>
        <item display="" display1="" id="10" comparision="!;>$+"/>
        <item display="" display1="" id="11" comparision="-,@:`"/>
        <item display="" display1="" id="12" comparision="|#{$-"/>
        <item display="" display1="" id="13" comparision="-#~&lt;&quot;"/>
        <item display="" display1="" id="14" comparision="?]}&amp;/"/>
        <item display="" display1="" id="15" comparision=".&amp;$'}"/>
        <item display="" display1="" id="16" comparision="~#/))"/>
        <item display="" display1="" id="17" comparision="{|~';"/>
        <item display="" display1="" id="18" comparision=")[?&lt;-"/>
        <item display="" display1="" id="19" comparision="]?:}%"/>
        <item display="" display1="" id="20" comparision="%?`(~"/>
        <item display="" display1="" id="21" comparision="\~#;@"/>
        <item display="" display1="" id="22" comparision=".&lt;::\"/>
        <item display="" display1="" id="23" comparision="}>?~["/>
        <item display="" display1="" id="24" comparision="^.(>["/>
        <item display="" display1="" id="25" comparision="[?/^%"/>
        <item display="" display1="" id="26" comparision="#*`('"/>
        <item display="" display1="" id="27" comparision="~;:^?"/>
        <item display="" display1="" id="28" comparision="&quot;!-=("/>
        <item display="" display1="" id="29" comparision="{%-,."/>
        <item display="" display1="" id="30" comparision=">&amp;]('"/>
        <item display="" display1="" id="31" comparision="$[-{*"/>
        <item display="" display1="" id="32" comparision="&quot;+%#?"/>
        <item display="" display1="" id="33" comparision="`](\/"/>
        <item display="" display1="" id="34" comparision=")&quot;&lt;&amp;&amp;"/>
        <item display="" display1="" id="35" comparision="%,_%!"/>
        <item display="" display1="" id="36" comparision="$-:?/"/>
        <item display="" display1="" id="37" comparision=")_/=~"/>
        <item display="" display1="" id="38" comparision="&lt;&lt;_^#"/>
        <item display="" display1="" id="39" comparision="/&amp;'}."/>
    </content>
</course>
