<!DOCTYPE x9.xml>
<course>
    <courseInfo security="==" new="false" alias="二字词9" courseType=""/>
    <content>
        <item display="" display1="" id="0" comparision="日记"/>
        <item display="" display1="" id="1" comparision="日夜"/>
        <item display="" display1="" id="2" comparision="遇险"/>
        <item display="" display1="" id="3" comparision="遇难"/>
        <item display="" display1="" id="4" comparision="遇到"/>
        <item display="" display1="" id="5" comparision="愚昧"/>
        <item display="" display1="" id="6" comparision="电工"/>
        <item display="" display1="" id="7" comparision="电子"/>
        <item display="" display1="" id="8" comparision="电能"/>
        <item display="" display1="" id="9" comparision="电台"/>
        <item display="" display1="" id="10" comparision="电大"/>
        <item display="" display1="" id="11" comparision="电压"/>
        <item display="" display1="" id="12" comparision="电磁"/>
        <item display="" display1="" id="13" comparision="电脑"/>
        <item display="" display1="" id="14" comparision="电动"/>
        <item display="" display1="" id="15" comparision="电教"/>
        <item display="" display1="" id="16" comparision="电表"/>
        <item display="" display1="" id="17" comparision="电池"/>
        <item display="" display1="" id="18" comparision="电源"/>
        <item display="" display1="" id="19" comparision="电流"/>
        <item display="" display1="" id="20" comparision="电影"/>
        <item display="" display1="" id="21" comparision="电路"/>
        <item display="" display1="" id="22" comparision="电器"/>
        <item display="" display1="" id="23" comparision="电车"/>
        <item display="" display1="" id="24" comparision="电力"/>
        <item display="" display1="" id="25" comparision="电网"/>
        <item display="" display1="" id="26" comparision="电焊"/>
        <item display="" display1="" id="27" comparision="电灯"/>
        <item display="" display1="" id="28" comparision="电炉"/>
        <item display="" display1="" id="29" comparision="电视"/>
        <item display="" display1="" id="30" comparision="电报"/>
        <item display="" display1="" id="31" comparision="电气"/>
        <item display="" display1="" id="32" comparision="电机"/>
        <item display="" display1="" id="33" comparision="电梯"/>
        <item display="" display1="" id="34" comparision="电站"/>
        <item display="" display1="" id="35" comparision="电线"/>
        <item display="" display1="" id="36" comparision="电讯"/>
        <item display="" display1="" id="37" comparision="电话"/>
        <item display="" display1="" id="38" comparision="显著"/>
        <item display="" display1="" id="39" comparision="显示"/>
        <item display="" display1="" id="40" comparision="显现"/>
        <item display="" display1="" id="41" comparision="显然"/>
        <item display="" display1="" id="42" comparision="显得"/>
        <item display="" display1="" id="43" comparision="晚期"/>
        <item display="" display1="" id="44" comparision="晚上"/>
        <item display="" display1="" id="45" comparision="昂贵"/>
        <item display="" display1="" id="46" comparision="晚饭"/>
        <item display="" display1="" id="47" comparision="晚报"/>
        <item display="" display1="" id="48" comparision="晚年"/>
        <item display="" display1="" id="49" comparision="晚间"/>
        <item display="" display1="" id="50" comparision="晚会"/>
        <item display="" display1="" id="51" comparision="果品"/>
        <item display="" display1="" id="52" comparision="果园"/>
        <item display="" display1="" id="53" comparision="果断"/>
        <item display="" display1="" id="54" comparision="果实"/>
        <item display="" display1="" id="55" comparision="果然"/>
        <item display="" display1="" id="56" comparision="果树"/>
        <item display="" display1="" id="57" comparision="星期"/>
        <item display="" display1="" id="58" comparision="昨天"/>
        <item display="" display1="" id="59" comparision="监督"/>
        <item display="" display1="" id="60" comparision="临时"/>
        <item display="" display1="" id="61" comparision="昨日"/>
        <item display="" display1="" id="62" comparision="昨晚"/>
        <item display="" display1="" id="63" comparision="鉴别"/>
        <item display="" display1="" id="64" comparision="临界"/>
        <item display="" display1="" id="65" comparision="星火"/>
        <item display="" display1="" id="66" comparision="鉴定"/>
        <item display="" display1="" id="67" comparision="监察"/>
        <item display="" display1="" id="68" comparision="监视"/>
        <item display="" display1="" id="69" comparision="监狱"/>
        <item display="" display1="" id="70" comparision="临近"/>
        <item display="" display1="" id="71" comparision="监禁"/>
        <item display="" display1="" id="72" comparision="临床"/>
        <item display="" display1="" id="73" comparision="蝉联"/>
        <item display="" display1="" id="74" comparision="暗示"/>
        <item display="" display1="" id="75" comparision="照顾"/>
        <item display="" display1="" id="76" comparision="归还"/>
        <item display="" display1="" id="77" comparision="照常"/>
        <item display="" display1="" id="78" comparision="照明"/>
        <item display="" display1="" id="79" comparision="归国"/>
        <item display="" display1="" id="80" comparision="归属"/>
        <item display="" display1="" id="81" comparision="照料"/>
        <item display="" display1="" id="82" comparision="照相"/>
        <item display="" display1="" id="83" comparision="照样"/>
        <item display="" display1="" id="84" comparision="照片"/>
        <item display="" display1="" id="85" comparision="归侨"/>
        <item display="" display1="" id="86" comparision="归纳"/>
        <item display="" display1="" id="87" comparision="昆明"/>
        <item display="" display1="" id="88" comparision="昆虫"/>
        <item display="" display1="" id="89" comparision="昆仑"/>
        <item display="" display1="" id="90" comparision="影子"/>
        <item display="" display1="" id="91" comparision="影院"/>
        <item display="" display1="" id="92" comparision="影响"/>
        <item display="" display1="" id="93" comparision="影视"/>
        <item display="" display1="" id="94" comparision="景色"/>
        <item display="" display1="" id="95" comparision="景象"/>
        <item display="" display1="" id="96" comparision="景气"/>
        <item display="" display1="" id="97" comparision="影片"/>
        <item display="" display1="" id="98" comparision="叹息"/>
        <item display="" display1="" id="99" comparision="顺利"/>
        <item display="" display1="" id="100" comparision="顺序"/>
        <item display="" display1="" id="101" comparision="吸取"/>
        <item display="" display1="" id="102" comparision="吸毒"/>
        <item display="" display1="" id="103" comparision="吸收"/>
        <item display="" display1="" id="104" comparision="吸引"/>
        <item display="" display1="" id="105" comparision="味道"/>
        <item display="" display1="" id="106" comparision="号码"/>
        <item display="" display1="" id="107" comparision="呈现"/>
        <item display="" display1="" id="108" comparision="号召"/>
        <item display="" display1="" id="109" comparision="哺育"/>
        <item display="" display1="" id="110" comparision="中东"/>
        <item display="" display1="" id="111" comparision="中医"/>
        <item display="" display1="" id="112" comparision="中药"/>
        <item display="" display1="" id="113" comparision="路子"/>
        <item display="" display1="" id="114" comparision="跟随"/>
        <item display="" display1="" id="115" comparision="贵阳"/>
        <item display="" display1="" id="116" comparision="中队"/>
        <item display="" display1="" id="117" comparision="中原"/>
        <item display="" display1="" id="118" comparision="跳动"/>
        <item display="" display1="" id="119" comparision="跃进"/>
        <item display="" display1="" id="120" comparision="中专"/>
        <item display="" display1="" id="121" comparision="足球"/>
        <item display="" display1="" id="122" comparision="中毒"/>
        <item display="" display1="" id="123" comparision="中肯"/>
        <item display="" display1="" id="124" comparision="跑步"/>
        <item display="" display1="" id="125" comparision="中学"/>
        <item display="" display1="" id="126" comparision="踊跃"/>
        <item display="" display1="" id="127" comparision="遗嘱"/>
        <item display="" display1="" id="128" comparision="中央"/>
        <item display="" display1="" id="129" comparision="中山"/>
        <item display="" display1="" id="130" comparision="中层"/>
        <item display="" display1="" id="131" comparision="中性"/>
        <item display="" display1="" id="132" comparision="中心"/>
        <item display="" display1="" id="133" comparision="中断"/>
        <item display="" display1="" id="134" comparision="贵宾"/>
        <item display="" display1="" id="135" comparision="踏实"/>
        <item display="" display1="" id="136" comparision="中外"/>
        <item display="" display1="" id="137" comparision="中旬"/>
        <item display="" display1="" id="138" comparision="足够"/>
        <item display="" display1="" id="139" comparision="中西"/>
        <item display="" display1="" id="140" comparision="中秋"/>
        <item display="" display1="" id="141" comparision="遗产"/>
        <item display="" display1="" id="142" comparision="中立"/>
        <item display="" display1="" id="143" comparision="中华"/>
        <item display="" display1="" id="144" comparision="路线"/>
        <item display="" display1="" id="145" comparision="中继"/>
        <item display="" display1="" id="146" comparision="距离"/>
        <item display="" display1="" id="147" comparision="忠诚"/>
        <item display="" display1="" id="148" comparision="跳高"/>
        <item display="" display1="" id="149" comparision="足迹"/>
        <item display="" display1="" id="150" comparision="贵州"/>
        <item display="" display1="" id="151" comparision="虽然"/>
        <item display="" display1="" id="152" comparision="唱歌"/>
        <item display="" display1="" id="153" comparision="唱片"/>
        <item display="" display1="" id="154" comparision="虽说"/>
        <item display="" display1="" id="155" comparision="口腔"/>
        <item display="" display1="" id="156" comparision="噪声"/>
        <item display="" display1="" id="157" comparision="器具"/>
        <item display="" display1="" id="158" comparision="口号"/>
        <item display="" display1="" id="159" comparision="口岸"/>
        <item display="" display1="" id="160" comparision="器官"/>
        <item display="" display1="" id="161" comparision="品质"/>
        <item display="" display1="" id="162" comparision="口气"/>
        <item display="" display1="" id="163" comparision="器械"/>
        <item display="" display1="" id="164" comparision="器材"/>
        <item display="" display1="" id="165" comparision="品格"/>
        <item display="" display1="" id="166" comparision="品德"/>
        <item display="" display1="" id="167" comparision="品种"/>
        <item display="" display1="" id="168" comparision="口头"/>
        <item display="" display1="" id="169" comparision="口袋"/>
        <item display="" display1="" id="170" comparision="器件"/>
        <item display="" display1="" id="171" comparision="口语"/>
        <item display="" display1="" id="172" comparision="别墅"/>
        <item display="" display1="" id="173" comparision="咖啡"/>
        <item display="" display1="" id="174" comparision="咽喉"/>
        <item display="" display1="" id="175" comparision="另外"/>
        <item display="" display1="" id="176" comparision="员工"/>
        <item display="" display1="" id="177" comparision="呐喊"/>
        <item display="" display1="" id="178" comparision="勋章"/>
        <item display="" display1="" id="179" comparision="嘱咐"/>
        <item display="" display1="" id="180" comparision="叫做"/>
        <item display="" display1="" id="181" comparision="史册"/>
        <item display="" display1="" id="182" comparision="史料"/>
        <item display="" display1="" id="183" comparision="兄弟"/>
        <item display="" display1="" id="184" comparision="史诗"/>
        <item display="" display1="" id="185" comparision="听取"/>
        <item display="" display1="" id="186" comparision="啤酒"/>
        <item display="" display1="" id="187" comparision="听见"/>
        <item display="" display1="" id="188" comparision="听众"/>
        <item display="" display1="" id="189" comparision="听说"/>
        <item display="" display1="" id="190" comparision="叮嘱"/>
        <item display="" display1="" id="191" comparision="吃苦"/>
        <item display="" display1="" id="192" comparision="吃喝"/>
        <item display="" display1="" id="193" comparision="吃惊"/>
        <item display="" display1="" id="194" comparision="吃饭"/>
        <item display="" display1="" id="195" comparision="咱们"/>
        <item display="" display1="" id="196" comparision="响应"/>
        <item display="" display1="" id="197" comparision="响亮"/>
        <item display="" display1="" id="198" comparision="哪些"/>
        <item display="" display1="" id="199" comparision="哪里"/>
        <item display="" display1="" id="200" comparision="哪怕"/>
        <item display="" display1="" id="201" comparision="哪儿"/>
        <item display="" display1="" id="202" comparision="哪个"/>
        <item display="" display1="" id="203" comparision="只限"/>
        <item display="" display1="" id="204" comparision="只能"/>
        <item display="" display1="" id="205" comparision="只顾"/>
        <item display="" display1="" id="206" comparision="只有"/>
        <item display="" display1="" id="207" comparision="只需"/>
        <item display="" display1="" id="208" comparision="唯一"/>
        <item display="" display1="" id="209" comparision="只是"/>
        <item display="" display1="" id="210" comparision="只见"/>
        <item display="" display1="" id="211" comparision="唯独"/>
        <item display="" display1="" id="212" comparision="只要"/>
        <item display="" display1="" id="213" comparision="只得"/>
        <item display="" display1="" id="214" comparision="只管"/>
        <item display="" display1="" id="215" comparision="只好"/>
        <item display="" display1="" id="216" comparision="轻工"/>
        <item display="" display1="" id="217" comparision="轻型"/>
        <item display="" display1="" id="218" comparision="轻易"/>
        <item display="" display1="" id="219" comparision="轻视"/>
        <item display="" display1="" id="220" comparision="轻松"/>
        <item display="" display1="" id="221" comparision="轻重"/>
        <item display="" display1="" id="222" comparision="轻微"/>
        <item display="" display1="" id="223" comparision="轻便"/>
        <item display="" display1="" id="224" comparision="因子"/>
        <item display="" display1="" id="225" comparision="固有"/>
        <item display="" display1="" id="226" comparision="因而"/>
        <item display="" display1="" id="227" comparision="罪恶"/>
        <item display="" display1="" id="228" comparision="因素"/>
        <item display="" display1="" id="229" comparision="因此"/>
        <item display="" display1="" id="230" comparision="固定"/>
        <item display="" display1="" id="231" comparision="固然"/>
        <item display="" display1="" id="232" comparision="罪名"/>
        <item display="" display1="" id="233" comparision="罪犯"/>
        <item display="" display1="" id="234" comparision="固体"/>
        <item display="" display1="" id="235" comparision="因为"/>
        <item display="" display1="" id="236" comparision="罢工"/>
        <item display="" display1="" id="237" comparision="园艺"/>
        <item display="" display1="" id="238" comparision="围攻"/>
        <item display="" display1="" id="239" comparision="罢了"/>
        <item display="" display1="" id="240" comparision="围观"/>
        <item display="" display1="" id="241" comparision="默契"/>
        <item display="" display1="" id="242" comparision="转达"/>
        <item display="" display1="" id="243" comparision="园地"/>
        <item display="" display1="" id="244" comparision="转动"/>
        <item display="" display1="" id="245" comparision="转眼"/>
        <item display="" display1="" id="246" comparision="黑暗"/>
        <item display="" display1="" id="247" comparision="团员"/>
        <item display="" display1="" id="248" comparision="默默"/>
        <item display="" display1="" id="249" comparision="团圆"/>
        <item display="" display1="" id="250" comparision="围困"/>
        <item display="" display1="" id="251" comparision="转发"/>
        <item display="" display1="" id="252" comparision="转业"/>
        <item display="" display1="" id="253" comparision="黑色"/>
        <item display="" display1="" id="254" comparision="转换"/>
        <item display="" display1="" id="255" comparision="转折"/>
        <item display="" display1="" id="256" comparision="转播"/>
        <item display="" display1="" id="257" comparision="围棋"/>
        <item display="" display1="" id="258" comparision="黑板"/>
        <item display="" display1="" id="259" comparision="园林"/>
        <item display="" display1="" id="260" comparision="团长"/>
        <item display="" display1="" id="261" comparision="转向"/>
        <item display="" display1="" id="262" comparision="转移"/>
        <item display="" display1="" id="263" comparision="团委"/>
        <item display="" display1="" id="264" comparision="转入"/>
        <item display="" display1="" id="265" comparision="转交"/>
        <item display="" display1="" id="266" comparision="转产"/>
        <item display="" display1="" id="267" comparision="团体"/>
        <item display="" display1="" id="268" comparision="黑人"/>
        <item display="" display1="" id="269" comparision="转化"/>
        <item display="" display1="" id="270" comparision="围绕"/>
        <item display="" display1="" id="271" comparision="团结"/>
        <item display="" display1="" id="272" comparision="转让"/>
        <item display="" display1="" id="273" comparision="转变"/>
        <item display="" display1="" id="274" comparision="车工"/>
        <item display="" display1="" id="275" comparision="国营"/>
        <item display="" display1="" id="276" comparision="国际"/>
        <item display="" display1="" id="277" comparision="车队"/>
        <item display="" display1="" id="278" comparision="国防"/>
        <item display="" display1="" id="279" comparision="车厢"/>
        <item display="" display1="" id="280" comparision="辅助"/>
        <item display="" display1="" id="281" comparision="国土"/>
        <item display="" display1="" id="282" comparision="国都"/>
        <item display="" display1="" id="283" comparision="国境"/>
        <item display="" display1="" id="284" comparision="国王"/>
        <item display="" display1="" id="285" comparision="国法"/>
        <item display="" display1="" id="286" comparision="车辆"/>
        <item display="" display1="" id="287" comparision="国力"/>
        <item display="" display1="" id="288" comparision="车轮"/>
        <item display="" display1="" id="289" comparision="国民"/>
        <item display="" display1="" id="290" comparision="辅导"/>
        <item display="" display1="" id="291" comparision="国家"/>
        <item display="" display1="" id="292" comparision="国宾"/>
        <item display="" display1="" id="293" comparision="国外"/>
        <item display="" display1="" id="294" comparision="车票"/>
        <item display="" display1="" id="295" comparision="国歌"/>
        <item display="" display1="" id="296" comparision="国籍"/>
        <item display="" display1="" id="297" comparision="国策"/>
        <item display="" display1="" id="298" comparision="国务"/>
        <item display="" display1="" id="299" comparision="国徽"/>
    </content>
</course>
