<!DOCTYPE x61.xml>
<course>
    <courseInfo security="E=" new="false" alias="多字词组1" courseType="wb-word"/>
    <content>
        <item display="" display1="" id="0" comparision="二十一世纪"/>
        <item display="" display1="" id="1" comparision="几内亚比绍"/>
        <item display="" display1="" id="2" comparision="有限责任公司"/>
        <item display="" display1="" id="3" comparision="法西斯主义"/>
        <item display="" display1="" id="4" comparision="一石激起千层浪"/>
        <item display="" display1="" id="5" comparision="君主立宪制"/>
        <item display="" display1="" id="6" comparision="磨刀不误砍柴工"/>
        <item display="" display1="" id="7" comparision="十一届三中全会"/>
        <item display="" display1="" id="8" comparision="英雄无用武之地"/>
        <item display="" display1="" id="9" comparision="贵人多忘事"/>
        <item display="" display1="" id="10" comparision="澳门特别行政区"/>
        <item display="" display1="" id="11" comparision="风马牛不相及"/>
        <item display="" display1="" id="12" comparision="山高皇帝远"/>
        <item display="" display1="" id="13" comparision="有志者事竟成"/>
        <item display="" display1="" id="14" comparision="有钱能使鬼推磨"/>
        <item display="" display1="" id="15" comparision="无风不起浪"/>
        <item display="" display1="" id="16" comparision="天时地利人和"/>
        <item display="" display1="" id="17" comparision="万变不离其宗"/>
        <item display="" display1="" id="18" comparision="中国共产党"/>
        <item display="" display1="" id="19" comparision="军中无戏言"/>
        <item display="" display1="" id="20" comparision="新疆维吾尔自治区"/>
        <item display="" display1="" id="21" comparision="高不成低不就"/>
        <item display="" display1="" id="22" comparision="世界贸易组织"/>
        <item display="" display1="" id="23" comparision="天公不作美"/>
        <item display="" display1="" id="24" comparision="群起而攻之"/>
        <item display="" display1="" id="25" comparision="牵着鼻子走"/>
        <item display="" display1="" id="26" comparision="马绍尔群岛"/>
        <item display="" display1="" id="27" comparision="里约热内卢"/>
        <item display="" display1="" id="28" comparision="九牛二虎之力"/>
        <item display="" display1="" id="29" comparision="打肿脸充胖子"/>
        <item display="" display1="" id="30" comparision="可望而不可即"/>
        <item display="" display1="" id="31" comparision="文化大革命"/>
        <item display="" display1="" id="32" comparision="斯洛文尼亚"/>
        <item display="" display1="" id="33" comparision="王顾左右而言他"/>
        <item display="" display1="" id="34" comparision="十万八千里"/>
        <item display="" display1="" id="35" comparision="疑心生暗鬼"/>
        <item display="" display1="" id="36" comparision="马达加斯加"/>
        <item display="" display1="" id="37" comparision="内蒙古自治区"/>
        <item display="" display1="" id="38" comparision="狗嘴吐不出象牙"/>
        <item display="" display1="" id="39" comparision="天无绝人之路"/>
        <item display="" display1="" id="40" comparision="反其道而行之"/>
        <item display="" display1="" id="41" comparision="无所不用其极"/>
        <item display="" display1="" id="42" comparision="英雄所见略同"/>
        <item display="" display1="" id="43" comparision="天有不测风云"/>
        <item display="" display1="" id="44" comparision="但愿人长久"/>
        <item display="" display1="" id="45" comparision="脚踏两只船"/>
        <item display="" display1="" id="46" comparision="不识庐山真面目"/>
        <item display="" display1="" id="47" comparision="伊斯坦布尔"/>
        <item display="" display1="" id="48" comparision="阿姆斯特丹"/>
        <item display="" display1="" id="49" comparision="救民于水火"/>
        <item display="" display1="" id="50" comparision="全民所有制"/>
        <item display="" display1="" id="51" comparision="隔行如隔山"/>
        <item display="" display1="" id="52" comparision="新官上任三把火"/>
        <item display="" display1="" id="53" comparision="司马昭之心"/>
        <item display="" display1="" id="54" comparision="女大十八变"/>
        <item display="" display1="" id="55" comparision="一失足成千古恨"/>
        <item display="" display1="" id="56" comparision="事实胜于雄辩"/>
        <item display="" display1="" id="57" comparision="胜败乃兵家常事"/>
        <item display="" display1="" id="58" comparision="阿拉伯联合酋长国"/>
        <item display="" display1="" id="59" comparision="打开天窗说亮话"/>
        <item display="" display1="" id="60" comparision="亚里士多德"/>
        <item display="" display1="" id="61" comparision="无巧不成书"/>
        <item display="" display1="" id="62" comparision="欲速则不达"/>
        <item display="" display1="" id="63" comparision="如入无人之境"/>
        <item display="" display1="" id="64" comparision="广西壮族自治区"/>
        <item display="" display1="" id="65" comparision="名不正则言不顺"/>
        <item display="" display1="" id="66" comparision="不管三七二十一"/>
        <item display="" display1="" id="67" comparision="皮笑肉不笑"/>
        <item display="" display1="" id="68" comparision="做一天和尚撞一天钟"/>
        <item display="" display1="" id="69" comparision="唯恐天下不乱"/>
        <item display="" display1="" id="70" comparision="反其道而行"/>
        <item display="" display1="" id="71" comparision="知其不可而为之"/>
        <item display="" display1="" id="72" comparision="联产承包责任制"/>
        <item display="" display1="" id="73" comparision="三思而后行"/>
        <item display="" display1="" id="74" comparision="情人眼里出西施"/>
        <item display="" display1="" id="75" comparision="口惠而实不至"/>
        <item display="" display1="" id="76" comparision="富贵不能淫"/>
        <item display="" display1="" id="77" comparision="土库曼斯坦"/>
        <item display="" display1="" id="78" comparision="醉翁之意不在酒"/>
        <item display="" display1="" id="79" comparision="初生牛犊不怕虎"/>
        <item display="" display1="" id="80" comparision="法属圭亚那"/>
        <item display="" display1="" id="81" comparision="农林牧副渔"/>
        <item display="" display1="" id="82" comparision="吃不了兜着走"/>
        <item display="" display1="" id="83" comparision="换汤不换药"/>
        <item display="" display1="" id="84" comparision="无可无不可"/>
        <item display="" display1="" id="85" comparision="杯酒释兵权"/>
        <item display="" display1="" id="86" comparision="人民代表大会"/>
        <item display="" display1="" id="87" comparision="狄俄尼索斯"/>
        <item display="" display1="" id="88" comparision="巴布亚新几内亚"/>
        <item display="" display1="" id="89" comparision="一个巴掌拍不响"/>
        <item display="" display1="" id="90" comparision="知子莫若父"/>
        <item display="" display1="" id="91" comparision="拉斯维加斯"/>
        <item display="" display1="" id="92" comparision="真金不怕火炼"/>
        <item display="" display1="" id="93" comparision="杀鸡用牛刀"/>
        <item display="" display1="" id="94" comparision="西藏自治区"/>
        <item display="" display1="" id="95" comparision="学而优则仕"/>
        <item display="" display1="" id="96" comparision="小米加步枪"/>
        <item display="" display1="" id="97" comparision="挂羊头卖狗肉"/>
        <item display="" display1="" id="98" comparision="戈尔巴乔夫"/>
        <item display="" display1="" id="99" comparision="阿尔及利亚"/>
    </content>
</course>
